notletters/__init__.py
notletters/client.py
notletters/exceptions.py
notletters/methods.py
notletters/py.typed
notletters/responses.py
notletters-0.1.2.dist-info/METADATA
notletters-0.1.2.dist-info/WHEEL
notletters-0.1.2.dist-info/licenses/LICENSE
notletters-0.1.2.dist-info/RECORD
