Metadata-Version: 2.4
Name: notletters
Version: 0.1.2
Summary: A lightweight NotLetters SDK based on stollen.
Project-URL: Homepage, https://git.notletters.com/notletters/notletters-python.git
Project-URL: Issues, https://git.notletters.com/notletters/notletters-python/issues
Project-URL: Repository, https://git.notletters.com/notletters/notletters-python.git
Author: LORES
License-File: LICENSE
Keywords: letters,mails,notletters,sdk
Classifier: Programming Language :: Python :: 3 :: Only
Classifier: Programming Language :: Python :: 3.9
Classifier: Programming Language :: Python :: 3.10
Classifier: Programming Language :: Python :: 3.11
Classifier: Programming Language :: Python :: 3.12
Classifier: Programming Language :: Python :: 3.13
Requires-Python: >=3.9
Requires-Dist: stollen>=0.6.8
